api_endpoint_manager/__init__.py
api_endpoint_manager/api_endpoint.py
api_endpoint_manager/delete.py
api_endpoint_manager/get.py
api_endpoint_manager/post.py
api_endpoint_manager/put.py
api_endpoint_manager-0.0.12.dist-info/LICENSE
api_endpoint_manager-0.0.12.dist-info/METADATA
api_endpoint_manager-0.0.12.dist-info/WHEEL
api_endpoint_manager-0.0.12.dist-info/top_level.txt
api_endpoint_manager-0.0.12.dist-info/RECORD
