Metadata-Version: 2.1
Name: api-endpoint-manager
Version: 0.0.12
Summary: This library contains classes to simplify the process of Flask API end points definition
Home-page: https://github.com/Quakingaspen-codehub/api_endpoint_manager
Author: Quaking Aspen
Author-email: info@quakingaspen.net
License: MIT
Platform: UNKNOWN
Classifier: Programming Language :: Python :: 3
Classifier: License :: OSI Approved :: MIT License
Classifier: Operating System :: OS Independent
Requires-Python: >=3.6
License-File: LICENSE
Requires-Dist: http-request-response (>=0.0.25)
Requires-Dist: http-request-args
Requires-Dist: flask-jwt-auth
Requires-Dist: flask-restplus
